nsthread/__init__.py
nsthread/exception.py
nsthread/futures.py
nsthread/process.py
nsthread/production.py
nsthread/qthread.py
nsthread/singleton.py
nsthread/thread.py
nsthread/wraps.py
nsthread-0.0.7.dist-info/METADATA
nsthread-0.0.7.dist-info/WHEEL
nsthread-0.0.7.dist-info/top_level.txt
nsthread-0.0.7.dist-info/RECORD
