Metadata-Version: 2.4
Name: nsthread
Version: 0.0.7
Summary: 一个全面的Python并发编程增强库，为标准线程、进程和Qt线程提供了更高级的抽象和异常处理机制
Author-email: sandorn <sandorn@live.cn>
License: MIT
Project-URL: Homepage, https://github.com/sandorn/nsthread
Project-URL: Repository, https://github.com/sandorn/nsthread
Project-URL: Issues, https://github.com/sandorn/nsthread/issues
Keywords: thread,multithreading,multiprocessing,concurrency,parallelism,PyQt,async,futures
Classifier: Development Status :: 4 - Beta
Classifier: Intended Audience :: Developers
Classifier: License :: OSI Approved :: MIT License
Classifier: Programming Language :: Python :: 3.13
Classifier: Topic :: Software Development :: Libraries :: Python Modules
Classifier: Topic :: System :: Networking
Classifier: Topic :: System :: Distributed Computing
Requires-Python: >=3.13
Requires-Dist: psutil>=5.9.0
Provides-Extra: qt
Requires-Dist: PyQt6>=6.0.0; extra == "qt"
